Metadata-Version: 2.1
Name: eoscdt
Version: 0.1.7
Summary: eoscdt project
Home-page: UNKNOWN
Author: The EOSCDT Team
License: MIT
Platform: UNKNOWN
License-File: LICENSE
